{
    "message": null,
    "obj": [{
        "ID": "4321141716914437935071023",
        "ORG_UNIT_NAME": "北京分院",
        "ORG_CLASS": "BRCH",
        "FATHER_ORG_ID": "4321141681691813123941027",
        "ORG_UNIT_RGN": "北京"
    }, {
        "ID": "4321133316914437935071111",
        "ORG_UNIT_NAME": "沈阳分院",
        "ORG_CLASS": "BRCH",
        "FATHER_ORG_ID": "4321141681691813123941027",
        "ORG_UNIT_RGN": "沈阳"
    }, {
        "ID": "4321141716928289133561028",
        "ORG_UNIT_NAME": "上海分院",
        "ORG_CLASS": "BRCH",
        "FATHER_ORG_ID": "4321141681691813123941027",
        "ORG_UNIT_RGN": "上海"
    }, {
        "ID": "4321133316914437935071119",
        "ORG_UNIT_NAME": "兰州分院",
        "ORG_CLASS": "BRCH",
        "FATHER_ORG_ID": "4321141681691813123941027",
        "ORG_UNIT_RGN": "兰州"
    }, {
        "ID": "4321133316914437935071118",
        "ORG_UNIT_NAME": "西安分院",
        "ORG_CLASS": "BRCH",
        "FATHER_ORG_ID": "4321141681691813123941027",
        "ORG_UNIT_RGN": "西安"
    }, {
        "ID": "4321133316914437935071117",
        "ORG_UNIT_NAME": "昆明分院",
        "ORG_CLASS": "BRCH",
        "FATHER_ORG_ID": "4321141681691813123941027",
        "ORG_UNIT_RGN": "昆明"
    }, {
        "ID": "4321133316914437935071116",
        "ORG_UNIT_NAME": "成都分院",
        "ORG_CLASS": "BRCH",
        "FATHER_ORG_ID": "4321141681691813123941027",
        "ORG_UNIT_RGN": "成都"
    }, {
        "ID": "4321133316914437935071115",
        "ORG_UNIT_NAME": "广州分院",
        "ORG_CLASS": "BRCH",
        "FATHER_ORG_ID": "4321141681691813123941027",
        "ORG_UNIT_RGN": "广州"
    }, {
        "ID": "4321133316914437935071114",
        "ORG_UNIT_NAME": "武汉分院",
        "ORG_CLASS": "BRCH",
        "FATHER_ORG_ID": "4321141681691813123941027",
        "ORG_UNIT_RGN": "武汉"
    }, {
        "ID": "4321133316914437935071113",
        "ORG_UNIT_NAME": "南京分院",
        "ORG_CLASS": "BRCH",
        "FATHER_ORG_ID": "4321141681691813123941027",
        "ORG_UNIT_RGN": "南京"
    }, {
        "ID": "4321133316914437935071112",
        "ORG_UNIT_NAME": "长春分院",
        "ORG_CLASS": "BRCH",
        "FATHER_ORG_ID": "4321141681691813123941027",
        "ORG_UNIT_RGN": "长春"
    }],
    "pageInfo": null,
    "success": true
}
