[
	{
		"id": "001",
		"name": "院机关",
		"children": [
			{
				"id": "0011",
				"name": "办公厅",
				"children": [
					{
						"id": "00101",
						"name": "综合处"
					}, {
						"id": "00102",
						"name": "政策研究室"
					}, {
						"id": "00103",
						"name": "秘书室"
					}, {
						"id": "00104",
						"name": "文书处"
					}, {
						"id": "00105",
						"name": "安全保卫处"
					}, {
						"id": "00106",
						"name": "保密处"
					}
				]
			}, {
				"id": "0012",
				"name": "学部工作局"
			}, {
				"id": "0013",
				"name": "前沿科学与教育局"
			}
		]
	}, {
		"id": "002",
		"name": "分院",
	}, {
		"id": "003",
		"name": "卓越创新中心",
	}, {
		"id": "004",
		"name": "创新研究院",
	}, {
		"id": "005",
		"name": "大科学中心",
	}, {
		"id": "006",
		"name": "特色研究所",
	}, {
		"id": "007",
		"name": "其他研究单位",
	}, {
		"id": "008",
		"name": "学校及支撑机构",
	}, {
		"id": "009",
		"name": "共建单位",
	}, {
		"id": "010",
		"name": "企业",
	}, 
]