{
	"message": null,
	"obj": [{
		"RN": "1",
		"ID": "1425005273149103333543247",
		"ORG_UNIT_ID": "1421924106089631410343354",
		"JOBS_CODE": "ZKY001",
		"JOBS_NAME": "经理",
		"JOBS_TYPE": "218",
		"SEQ_NO": "1",
		"DATA_ENABLE": "ACT",
		"JOBS_DESC": "领导小组",
		"MEMO": null,
		"JOBS_REQ": null,
		"staffCount": "3",
		"JOBS_TYPE_HR_JOBS_TYPE": "科研秘书",
		"DATA_ENABLE_SYSTEM_DATA_ENABLE": "启用"
	}, {
		"RN": "2",
		"ID": "1421991949000935810413279",
		"ORG_UNIT_ID": "1421924106089631410343354",
		"JOBS_CODE": "1111",
		"JOBS_NAME": "需求分析师",
		"JOBS_TYPE": "219",
		"SEQ_NO": "2",
		"DATA_ENABLE": "ACT",
		"JOBS_DESC": "需求分析",
		"MEMO": "11",
		"JOBS_REQ": "213123",
		"staffCount": "9",
		"JOBS_TYPE_HR_JOBS_TYPE": "挂靠学会",
		"DATA_ENABLE_SYSTEM_DATA_ENABLE": "启用"
	}, {
		"RN": "3",
		"ID": "1422239004474196010273279",
		"ORG_UNIT_ID": "1421924106089631410343354",
		"JOBS_CODE": "test",
		"JOBS_NAME": "测试岗位111111",
		"JOBS_TYPE": "101",
		"SEQ_NO": "3",
		"DATA_ENABLE": "ACT",
		"JOBS_DESC": "测试岗位管理模块，提交Bug",
		"MEMO": "1233",
		"JOBS_REQ": "善于发现",
		"staffCount": "4",
		"JOBS_TYPE_HR_JOBS_TYPE": "基础研究",
		"DATA_ENABLE_SYSTEM_DATA_ENABLE": "启用"
	}, {
		"RN": "4",
		"ID": "1421997979552288010413279",
		"ORG_UNIT_ID": "1421924106089631410343354",
		"JOBS_CODE": "FCZ",
		"JOBS_NAME": "科研秘书1",
		"JOBS_TYPE": "218",
		"SEQ_NO": "4",
		"DATA_ENABLE": "ACT",
		"JOBS_DESC": "天职",
		"MEMO": "吃害虫2",
		"JOBS_REQ": null,
		"staffCount": "7",
		"JOBS_TYPE_HR_JOBS_TYPE": "科研秘书",
		"DATA_ENABLE_SYSTEM_DATA_ENABLE": "启用"
	}, {
		"RN": "5",
		"ID": "1431054449643104429356953",
		"ORG_UNIT_ID": "1421924106089631410343354",
		"JOBS_CODE": "kn2015",
		"JOBS_NAME": "程序员安慰师",
		"JOBS_TYPE": "212",
		"SEQ_NO": "5",
		"DATA_ENABLE": "ACT",
		"JOBS_DESC": "安慰程序员受伤的心灵",
		"MEMO": "强烈要求",
		"JOBS_REQ": "女神",
		"staffCount": "0",
		"JOBS_TYPE_HR_JOBS_TYPE": "大型仪器实验分析",
		"DATA_ENABLE_SYSTEM_DATA_ENABLE": "启用"
	}, {
		"RN": "6",
		"ID": "1422925890384466310313354",
		"ORG_UNIT_ID": "1421924106089631410343354",
		"JOBS_CODE": "11XTJGS",
		"JOBS_NAME": "系统架构师",
		"JOBS_TYPE": "215",
		"SEQ_NO": "6",
		"DATA_ENABLE": "ACT",
		"JOBS_DESC": "ARP3.0系统架构",
		"MEMO": null,
		"JOBS_REQ": "研究生，5年经验",
		"staffCount": "21",
		"JOBS_TYPE_HR_JOBS_TYPE": "标本馆、博物馆",
		"DATA_ENABLE_SYSTEM_DATA_ENABLE": "启用"
	}, {
		"RN": "7",
		"ID": "1431398593133104505715095",
		"ORG_UNIT_ID": "1421924106089631410343354",
		"JOBS_CODE": "23165",
		"JOBS_NAME": "人事主管",
		"JOBS_TYPE": "4",
		"SEQ_NO": "7",
		"DATA_ENABLE": "ACT",
		"JOBS_DESC": "负责HR工作",
		"MEMO": null,
		"JOBS_REQ": null,
		"staffCount": "11",
		"JOBS_TYPE_HR_JOBS_TYPE": "管理工作",
		"DATA_ENABLE_SYSTEM_DATA_ENABLE": "启用"
	}, {
		"RN": "8",
		"ID": "1422944196055377610303354",
		"ORG_UNIT_ID": "1421924106089631410343354",
		"JOBS_CODE": "QDGCS",
		"JOBS_NAME": "前端工程师",
		"JOBS_TYPE": "101",
		"SEQ_NO": "8",
		"DATA_ENABLE": "ACT",
		"JOBS_DESC": "ARP3.0前段开发",
		"MEMO": "前段开发组，angularJS",
		"JOBS_REQ": "是妹子",
		"staffCount": "8",
		"JOBS_TYPE_HR_JOBS_TYPE": "基础研究",
		"DATA_ENABLE_SYSTEM_DATA_ENABLE": "启用"
	}, {
		"RN": "9",
		"ID": "1421981877685502310333279",
		"ORG_UNIT_ID": "1421924106089631410343354",
		"JOBS_CODE": "fychang",
		"JOBS_NAME": "java工程师",
		"JOBS_TYPE": "1",
		"SEQ_NO": "9",
		"DATA_ENABLE": "ACT",
		"JOBS_DESC": "作为一名JAVA开发人员，我的职责是……",
		"MEMO": "作为一名开发人员，我的职责是……",
		"JOBS_REQ": null,
		"staffCount": "48",
		"JOBS_TYPE_HR_JOBS_TYPE": "研究技术工作",
		"DATA_ENABLE_SYSTEM_DATA_ENABLE": "启用"
	}, {
		"RN": "10",
		"ID": "1423029135155881610283279",
		"ORG_UNIT_ID": "1421924106089631410343354",
		"JOBS_CODE": "code",
		"JOBS_NAME": "程序测试",
		"JOBS_TYPE": "1",
		"SEQ_NO": "10",
		"DATA_ENABLE": "ACT",
		"JOBS_DESC": "努力工作",
		"MEMO": "我看看",
		"JOBS_REQ": "好的",
		"staffCount": "3",
		"JOBS_TYPE_HR_JOBS_TYPE": "研究技术工作",
		"DATA_ENABLE_SYSTEM_DATA_ENABLE": "启用"
	}],
	"pageInfo": {
		"page": 1,
		"pagesize": 10,
		"count": 34
	},
	"success": true
}